aiosupabase/__init__.py
aiosupabase/client.py
aiosupabase/version.py
aiosupabase/schemas/__init__.py
aiosupabase/schemas/auth.py
aiosupabase/schemas/funcs.py
aiosupabase/schemas/pgrest.py
aiosupabase/schemas/rt.py
aiosupabase/schemas/storage.py
aiosupabase/types/__init__.py
aiosupabase/types/errors.py
aiosupabase/utils/__init__.py
aiosupabase/utils/config.py
aiosupabase-0.0.4.dist-info/LICENSE
aiosupabase-0.0.4.dist-info/METADATA
aiosupabase-0.0.4.dist-info/WHEEL
aiosupabase-0.0.4.dist-info/top_level.txt
aiosupabase-0.0.4.dist-info/RECORD
