Metadata-Version: 2.1
Name: aiosupabase
Version: 0.0.4
Summary: Unofficial Asyncronous Python Client for Supabase
Home-page: https://github.com/trisongz/aiosupabase
Author: Tri Songz
Author-email: ts@growthengineai.com
License: MIT License
Classifier: Intended Audience :: Developers
Classifier: License :: OSI Approved :: MIT License
Classifier: Programming Language :: Python :: 3.7
Classifier: Topic :: Software Development :: Libraries
License-File: LICENSE
Requires-Dist: aiohttpx
Requires-Dist: lazyops
Requires-Dist: postgrest-py (==0.10.3)
Requires-Dist: gotrue (==0.5.4)
Requires-Dist: realtime (==0.0.5)
Requires-Dist: storage3 (==0.3.5)
